plateletanalysis/__init__.py
plateletanalysis/analysis/__init__.py
plateletanalysis/analysis/mips_analysis.py
plateletanalysis/analysis/peaks_analysis.py
plateletanalysis/analysis/plots.py
plateletanalysis/analysis/stats.py
plateletanalysis/analysis/summary_measures.py
plateletanalysis/topology/__init__.py
plateletanalysis/topology/animations.py
plateletanalysis/topology/donutness.py
plateletanalysis/topology/simulations.py
plateletanalysis/variables/__init__.py
plateletanalysis/variables/basic.py
plateletanalysis/variables/calcium.py
plateletanalysis/variables/measure.py
plateletanalysis/variables/neighbours.py
plateletanalysis/variables/transform.py
plateletanalysis-0.0.4.dist-info/LICENSE
plateletanalysis-0.0.4.dist-info/METADATA
plateletanalysis-0.0.4.dist-info/WHEEL
plateletanalysis-0.0.4.dist-info/top_level.txt
plateletanalysis-0.0.4.dist-info/RECORD
