Metadata-Version: 2.1
Name: plateletanalysis
Version: 0.0.4
Summary: plateletanalysis
Home-page: https://github.com/abigailmcgovern/platelet-analysis
Author: Abigail S McGovern & Niklas Boknas
Author-email: Abigail.McGovern1@monash.edu
License: BSD-3-Clause
Project-URL: Bug Tracker, https://github.com/abigailmcgovern/platelet-analysis/issues
Classifier: Development Status :: 2 - Pre-Alpha
Classifier: Intended Audience :: Science/Research
Classifier: Programming Language :: Python
Classifier: Programming Language :: Python :: 3
Classifier: Programming Language :: Python :: 3.9
Classifier: Programming Language :: Python :: 3.10
Classifier: Programming Language :: Python :: 3.11
Classifier: Operating System :: OS Independent
Classifier: License :: OSI Approved :: BSD License
Requires-Python: >=3.7
License-File: LICENSE
Requires-Dist: numpy >=1.26.1
Requires-Dist: pandas >=2.1.2
Requires-Dist: matplotlib >=3.8.1
Requires-Dist: scipy >=1.11.3
Requires-Dist: scikit-learn >=1.3.2
Requires-Dist: pyarrow >=14.0.1
Requires-Dist: fastparquet >=2023.10.1
Requires-Dist: napari >=0.4.18
Requires-Dist: scikit-image >=0.22.0
Requires-Dist: magicgui >=0.8.0
Requires-Dist: umap-learn >=0.5.4
Requires-Dist: dask >=2023.10.1
Requires-Dist: distributed >=2023.10.1
Requires-Dist: seaborn >=0.11.0
Requires-Dist: zarr >=2.16.1
Provides-Extra: donut
Requires-Dist: ripser >=0.6.4 ; extra == 'donut'
Provides-Extra: dtw
Requires-Dist: dtaidistance ; extra == 'dtw'
